event_scheduler/__init__.py
event_scheduler/scheduler.py
tankeventhandler-0.2.dist-info/LICENCE
tankeventhandler-0.2.dist-info/METADATA
tankeventhandler-0.2.dist-info/WHEEL
tankeventhandler-0.2.dist-info/top_level.txt
tankeventhandler-0.2.dist-info/RECORD
