Metadata-Version: 2.1
Name: tankeventhandler
Version: 0.2
Summary: The EventScheduler library allows users to schedule events to be triggered
Author: Bhaskar Tank
Author-email: tankbhaskar@gmail.com
License-File: LICENCE
